Metadata-Version: 2.1
Name: dpython
Version: 1.0.5
Summary: Modify python built-in functions and libraries
Home-page: https://github.com/Madoshakalaka/dark-python
Author: Matt Yan
Author-email: syan4@ualberta.ca
License: UNKNOWN
Project-URL: Bug Reports, https://github.com/Madoshakalaka/dark-python/issues
Project-URL: Funding, https://github.com/Madoshakalaka/dark-python
Project-URL: Say Thanks!, https://github.com/Madoshakalaka/dark-python
Project-URL: Source, https://github.com/Madoshakalaka/dark-python
Platform: UNKNOWN
Classifier: Development Status :: 3 - Alpha
Classifier: Intended Audience :: Developers
Classifier: Topic :: Software Development :: Build Tools
Classifier: License :: OSI Approved :: MIT License
Classifier: Programming Language :: Python :: 3.5
Classifier: Programming Language :: Python :: 3.6
Classifier: Programming Language :: Python :: 3.7
Requires-Python: >=3.5
